pinecone/__environment__
pinecone/__init__.py
pinecone/__version__
pinecone/config.py
pinecone/core/__init__.py
pinecone/core/api_action.py
pinecone/core/api_base.py
pinecone/core/client/__init__.py
pinecone/core/client/api/__init__.py
pinecone/core/client/api/index_operations_api.py
pinecone/core/client/api/vector_operations_api.py
pinecone/core/client/api_client.py
pinecone/core/client/apis/__init__.py
pinecone/core/client/configuration.py
pinecone/core/client/exceptions.py
pinecone/core/client/model/__init__.py
pinecone/core/client/model/approximated_config.py
pinecone/core/client/model/collection_meta.py
pinecone/core/client/model/create_collection_request.py
pinecone/core/client/model/create_request.py
pinecone/core/client/model/delete_request.py
pinecone/core/client/model/describe_index_stats_request.py
pinecone/core/client/model/describe_index_stats_response.py
pinecone/core/client/model/fetch_response.py
pinecone/core/client/model/hnsw_config.py
pinecone/core/client/model/index_meta.py
pinecone/core/client/model/index_meta_database.py
pinecone/core/client/model/index_meta_database_status.py
pinecone/core/client/model/index_meta_status.py
pinecone/core/client/model/namespace_summary.py
pinecone/core/client/model/patch_request.py
pinecone/core/client/model/protobuf_any.py
pinecone/core/client/model/protobuf_null_value.py
pinecone/core/client/model/query_request.py
pinecone/core/client/model/query_response.py
pinecone/core/client/model/query_vector.py
pinecone/core/client/model/rpc_status.py
pinecone/core/client/model/scored_vector.py
pinecone/core/client/model/single_query_results.py
pinecone/core/client/model/sparse_values.py
pinecone/core/client/model/update_request.py
pinecone/core/client/model/upsert_request.py
pinecone/core/client/model/upsert_response.py
pinecone/core/client/model/vector.py
pinecone/core/client/model_utils.py
pinecone/core/client/models/__init__.py
pinecone/core/client/rest.py
pinecone/core/exceptions.py
pinecone/core/grpc/__init__.py
pinecone_client_nightly-2.2.4.dist-info/LICENSE.txt
pinecone_client_nightly-2.2.4.dist-info/METADATA
pinecone_client_nightly-2.2.4.dist-info/WHEEL
pinecone_client_nightly-2.2.4.dist-info/RECORD
